apswutils/__init__.py
apswutils/_modidx.py
apswutils/db.py
apswutils/utils.py
apswutils-0.1.1.dist-info/licenses/LICENSE
apswutils-0.1.1.dist-info/METADATA
apswutils-0.1.1.dist-info/WHEEL
apswutils-0.1.1.dist-info/entry_points.txt
apswutils-0.1.1.dist-info/top_level.txt
apswutils-0.1.1.dist-info/RECORD
