Metadata-Version: 2.4
Name: apswutils
Version: 0.1.1
Summary: A fork of sqlite-minutils for apsw
Home-page: https://github.com/AnswerDotAI/apswutils
Author: Daniel and Audrey Roy Greenfeld, and Jeremy Howard
Author-email: info@fast.ai
License: Apache Software License 2.0
Keywords: nbdev jupyter notebook python sqlite apsw
Classifier: Development Status :: 4 - Beta
Classifier: Intended Audience :: Developers
Classifier: Natural Language :: English
Classifier: Programming Language :: Python :: 3.9
Classifier: Programming Language :: Python :: 3.10
Classifier: License :: OSI Approved :: Apache Software License
Requires-Python: >=3.9
License-File: LICENSE
Requires-Dist: fastcore
Requires-Dist: apsw
Provides-Extra: dev
Dynamic: author
Dynamic: author-email
Dynamic: classifier
Dynamic: description
Dynamic: description-content-type
Dynamic: home-page
Dynamic: keywords
Dynamic: license
Dynamic: license-file
Dynamic: provides-extra
Dynamic: requires-dist
Dynamic: requires-python
Dynamic: summary
